MANIFEST.in
README.md
setup.cfg
setup.py
antbot/__init__.py
antbot/__main__.py
antbot/ant.conf.example
antbot.egg-info/PKG-INFO
antbot.egg-info/SOURCES.txt
antbot.egg-info/dependency_links.txt
antbot.egg-info/entry_points.txt
antbot.egg-info/requires.txt
antbot.egg-info/top_level.txt