Metadata-Version: 1.1
Name: antbot
Version: 0.1.4
Summary: A slack chat bot doing scripts on the server
Home-page: https://github.com/yanganto/Ant
Author: yanganto
Author-email: yanganto@gmail.com
License: MIT
Keywords: slack,bot
Platform: UNKNOWN
Classifier: Programming Language :: Python
Classifier: Programming Language :: Python :: 3.5
Classifier: Programming Language :: Python :: 3.6
Classifier: Programming Language :: Python :: 3 :: Only
Classifier: Topic :: Communications :: Chat
